README.md
setup.py
tvn/__init__.py
tvn/config.py
tvn/data.py
tvn/data_augmentor.py
tvn/data_loader_av.py
tvn/data_loader_skvideo.py
tvn/data_parser.py
tvn/model.py
tvn/solver.py
tvn/transforms_video.py
tvn/utils.py
tvn.egg-info/PKG-INFO
tvn.egg-info/SOURCES.txt
tvn.egg-info/dependency_links.txt
tvn.egg-info/top_level.txt
tvn/cg/__init__.py
tvn/cg/cg_block.py
tvn/non_local/__init__.py
tvn/non_local/network.py
tvn/non_local/non_local_concatenation.py
tvn/non_local/non_local_dot_product.py
tvn/non_local/non_local_embedded_gaussian.py
tvn/non_local/non_local_gaussian.py
tvn/se/__init__.py
tvn/se/se_block.py
tvn/se/se_layer.py
tvn/temporal/__init__.py
tvn/temporal/temporal_blocks.py