Metadata-Version: 1.1
Name: tvn
Version: 1.0
Summary: Tiny Video Networks
Home-page: https://github.com/DELTA37/TVN.git
Author: George Kasparyants
Author-email: gkasparyants@gmail.com
License: UNKNOWN
Platform: UNKNOWN
Classifier: Programming Language :: Python :: 3
Classifier: License :: OSI Approved :: MIT License
Classifier: Operating System :: OS Independent
